mnlscript/__init__.py
mnlscript/bis/__init__.py
mnlscript/bis/commands.py
mnlscript/bis/consts.py
mnlscript/bis/globals.py
mnlscript/bis/misc.py
mnlscript/bis/text.py
mnlscript/bis/variables.py
mnlscript/commands.py
mnlscript/consts.py
mnlscript/dt/__init__.py
mnlscript/dt/commands.py
mnlscript/dt/consts.py
mnlscript/dt/globals.py
mnlscript/dt/misc.py
mnlscript/dt/sound.py
mnlscript/dt/text.py
mnlscript/dt/variables.py
mnlscript/globals.py
mnlscript/misc.py
mnlscript/py.typed
mnlscript/script.py
mnlscript/tools/__init__.py
mnlscript/tools/compiler/__init__.py
mnlscript/tools/compiler/bis.py
mnlscript/tools/compiler/dt.py
mnlscript/tools/compiler/misc.py
mnlscript/tools/consts.py
mnlscript/tools/decompiler/__init__.py
mnlscript/tools/decompiler/bis/__init__.py
mnlscript/tools/decompiler/bis/__main__.py
mnlscript/tools/decompiler/bis/command_matchers.py
mnlscript/tools/decompiler/bis/globals.py
mnlscript/tools/decompiler/bis/main.py
mnlscript/tools/decompiler/bis/misc.py
mnlscript/tools/decompiler/command_matchers.py
mnlscript/tools/decompiler/dt/__init__.py
mnlscript/tools/decompiler/dt/__main__.py
mnlscript/tools/decompiler/dt/command_matchers.py
mnlscript/tools/decompiler/dt/globals.py
mnlscript/tools/decompiler/dt/main.py
mnlscript/tools/decompiler/dt/misc.py
mnlscript/tools/decompiler/misc.py
mnlscript/utils.py
mnlscript/variables.py
mnlscript-0.2.5.dist-info/LICENSE
mnlscript-0.2.5.dist-info/METADATA
mnlscript-0.2.5.dist-info/WHEEL
mnlscript-0.2.5.dist-info/entry_points.txt
mnlscript-0.2.5.dist-info/RECORD
