Metadata-Version: 2.3
Name: mnlscript
Version: 0.2.5
Summary: Compiler and decompiler for the Mario & Luigi scripting language from and to Python.
License: LGPL-3.0-or-later
Author: Dimitar Dimitrov
Author-email: dmtrdmtrov@gmail.com
Requires-Python: >=3.12,<4.0
Classifier: License :: OSI Approved :: GNU Lesser General Public License v3 or later (LGPLv3+)
Classifier: Programming Language :: Python :: 3
Classifier: Programming Language :: Python :: 3.12
Classifier: Programming Language :: Python :: 3.13
Requires-Dist: bidict (>=0.23.1,<0.24.0)
Requires-Dist: dynamicscope (>=1.0.4,<2.0.0)
Requires-Dist: mnllib (>=0.2.0,<0.3.0)
Requires-Dist: more-itertools (>=10.5.0,<11.0.0)
Requires-Dist: numpy (>=2.2.3,<3.0.0)
Requires-Dist: pymsbmnl (>=1.1.0,<2.0.0)
Requires-Dist: tqdm (>=4.67.1,<5.0.0)
Project-URL: Repository, https://github.com/MnL-Modding/mnlscript.py
